simple_db_builder/__init__.py
simple_db_builder/builder.py
simple_db_builder/connections.py
simple_db_builder/helpers.py
simple_db_builder-0.1.dist-info/METADATA
simple_db_builder-0.1.dist-info/RECORD
simple_db_builder-0.1.dist-info/WHEEL
simple_db_builder-0.1.dist-info/top_level.txt
